mpt/__init__.py
mpt/config.py
mpt/console.py
mpt/functions.py
mpt/logger.py
mpt/settings.py
mpt/mpt-zsh-plugin/_mpt
mpt/scripts/frida/frida-bypass-root-detection.js
mpt/scripts/frida/frida-sslpinning-disable.js
mpt/scripts/template/frida-template.js
mptsec-0.7.60.dist-info/licenses/LICENSE
mptsec-0.7.60.dist-info/METADATA
mptsec-0.7.60.dist-info/WHEEL
mptsec-0.7.60.dist-info/entry_points.txt
mptsec-0.7.60.dist-info/top_level.txt
mptsec-0.7.60.dist-info/RECORD
