Metadata-Version: 2.4
Name: mptsec
Version: 0.7.60
Summary: Mobile Pentest Toolkit (MPT)
Author-email: Alexander Subbotin <dev@bytesnipers.com>
Project-URL: Homepage, https://github.com/ByteSnipers/mobile-pentest-toolkit
Project-URL: Repository, https://github.com/ByteSnipers/mobile-pentest-toolkit
Project-URL: Changelog, https://github.com/ByteSnipers/mobile-pentest-toolkit/blob/master/CHANGELOG.md
Keywords: MPT,Mobile,Pentesting
Classifier: Programming Language :: Python :: 3
Classifier: Operating System :: OS Independent
Requires-Python: >=3.9
License-File: LICENSE
Requires-Dist: GitPython
Requires-Dist: colorlog
Requires-Dist: colorama
Requires-Dist: tabulate
Requires-Dist: frida-tools
Requires-Dist: simple_term_menu
Requires-Dist: netifaces
Requires-Dist: poetry
Dynamic: license-file
